proto_clip_toolkit/__init__.py
proto_clip_toolkit/asr/__init__.py
proto_clip_toolkit/asr/asr_utils.py
proto_clip_toolkit/asr/transcribe.py
proto_clip_toolkit/asr/transcribe_with_pos.py
proto_clip_toolkit/pos/__init__.py
proto_clip_toolkit/pos/verb_and_noun_tagger.py
proto_clip_toolkit/utils/__init__.py
proto_clip_toolkit/utils/model_utils.py
proto_clip_toolkit/utils/ood_utils.py
proto_clip_toolkit/utils/tsne.py
proto_clip_toolkit-1.0.dist-info/LICENSE.txt
proto_clip_toolkit-1.0.dist-info/METADATA
proto_clip_toolkit-1.0.dist-info/WHEEL
proto_clip_toolkit-1.0.dist-info/top_level.txt
proto_clip_toolkit-1.0.dist-info/RECORD
