Metadata-Version: 2.1
Name: proto-clip-toolkit
Version: 1.0
Summary: A simple toolkit from Proto-CLIP demo that provies speech recognition, part-of-speech tagging and realworld robot demo APIs.
Home-page: https://github.com/IRVLUTD/Proto-CLIP
Author: IRVL-UTD: Intelligent Robotics and Vision Lab at the University of Texas at Dallas
Author-email: irvl.utd@gmail.com
License: MIT
Requires-Python: >=3.7
License-File: LICENSE.txt
Requires-Dist: openai-whisper
Requires-Dist: PyAudio >=0.2.13
Requires-Dist: flair >=0.12.2
Requires-Dist: SpeechRecognition >=3.10.0
Requires-Dist: torch
Requires-Dist: torchvision
